gizai/__init__.py
gizai/__main__.py
gizai/logger.py
gizai/urls.py
gizai/.abcli/abcli.sh
gizai/.abcli/actions.sh
gizai/.abcli/aka.sh
gizai/.abcli/build.sh
gizai/.abcli/giza.sh
gizai/.abcli/pdf.sh
gizai/.abcli/tests/build.sh
gizai/.abcli/tests/help.sh
gizai/.abcli/tests/version.sh
gizai/help/__init__.py
gizai/help/__main__.py
gizai/help/functions.py
gizai/tex/__init__.py
gizai/tex/__main__.py
gizai/tex/functions.py
gizai-7.341.1.dist-info/licenses/LICENSE
gizai-7.341.1.dist-info/METADATA
gizai-7.341.1.dist-info/WHEEL
gizai-7.341.1.dist-info/top_level.txt
gizai-7.341.1.dist-info/RECORD
